MANIFEST.in
README.txt
setup.py
otlpytools/Differ.py
otlpytools/Logger.py
otlpytools/__init__.py
otlpytools/log_config.yaml
otlpytools/splunk.py
otlpytools.egg-info/PKG-INFO
otlpytools.egg-info/SOURCES.txt
otlpytools.egg-info/dependency_links.txt
otlpytools.egg-info/entry_points.txt
otlpytools.egg-info/requires.txt
otlpytools.egg-info/top_level.txt