Metadata-Version: 2.1
Name: otlpytools
Version: 1.0.11
Summary: Log all python files, and push to Splunk
Home-page: UNKNOWN
Author: Stefan McShane
Author-email: stefan.mcshane@options-it.com
License: MIT
Platform: UNKNOWN
Classifier: License :: OSI Approved :: MIT License
Classifier: Programming Language :: Python :: 3
Classifier: Programming Language :: Python :: 3.7
